LICENSE
MANIFEST.in
README.rst
setup.py
django_firebase_authentication.egg-info/PKG-INFO
django_firebase_authentication.egg-info/SOURCES.txt
django_firebase_authentication.egg-info/dependency_links.txt
django_firebase_authentication.egg-info/requires.txt
django_firebase_authentication.egg-info/top_level.txt
firebase_authentication/__init__.py
firebase_authentication/authentication.py
firebase_authentication/exceptions.py
firebase_authentication/managers.py
firebase_authentication/mixins.py
firebase_authentication/models.py
firebase_authentication/serializers.py
firebase_authentication/migrations/0001_initial.py
firebase_authentication/migrations/0002_auto_20200527_0846.py
firebase_authentication/migrations/__init__.py