Metadata-Version: 1.0
Name: django-firebase-authentication
Version: 1.0.8
Summary: A DRF authentication provider for Google Firebase AS.
Home-page: UNKNOWN
Author: floydya
Author-email: xfloydya@gmail.com
License: BSD License
Platform: UNKNOWN
